setup.py
src/rdvactxt.py
src/rdvactxt.egg-info/PKG-INFO
src/rdvactxt.egg-info/SOURCES.txt
src/rdvactxt.egg-info/dependency_links.txt
src/rdvactxt.egg-info/top_level.txt