Metadata-Version: 2.1
Name: rdvactxt
Version: 0.0.1
Summary:  A demo app for Text Classification using LSTM Model
Author: Lagisetty Ravikiran
Author-email: kiranlravi8@gmail.com
